Metadata-Version: 1.2
Name: qftplib
Version: 1.0
Summary: Simple library to connect and interact to FTP/SFTP servers
Home-page: https://github.com/lfbos/qftplib
Author: Luis Boscan
Author-email: lboscannava@gmail.com
License: MIT
Platform: UNKNOWN
Classifier: Programming Language :: Python :: 3
Classifier: License :: OSI Approved :: MIT License
Classifier: Operating System :: OS Independent
Requires-Python: >=3.7
